setup.py
productemail/__init__.py
productemail.egg-info/PKG-INFO
productemail.egg-info/SOURCES.txt
productemail.egg-info/dependency_links.txt
productemail.egg-info/top_level.txt