Metadata-Version: 1.1
Name: productemail
Version: 0.0.1
Summary: Its the Api logging message for crud operations 
Home-page: UNKNOWN
Author: kirthikesh
Author-email: x21195391@student.ncirl.ie
License: UNKNOWN
Keywords: productemail
Platform: UNKNOWN
Classifier: Development Status :: 5 - Production/Stable
Classifier: Intended Audience :: Education
Classifier: Operating System :: Microsoft :: Windows :: Windows 10
Classifier: License :: OSI Approved :: MIT License
Classifier: Programming Language :: Python :: 3
